mlutilities/Classification/__init__.py
mlutilities/Classification/classification_widgets.py
mlutilities/Classification/metrics.py
mlutilities/Clustering/clustering_widgets.py
mlutilities/Clustering/utils.py
mlutilities/__init__.py
mlutilities/classification/__init__.py
mlutilities/classification/classification_widgets.py
mlutilities/classification/plots.py
mlutilities/datasets/__init__.py
mlutilities/datasets/data/adults.pkl
mlutilities/datasets/data/cars.pkl
mlutilities/datasets/data/cars_noisy.pkl
mlutilities/datasets/data/diamonds.pkl
mlutilities/datasets/data/diamonds_noisy.pkl
mlutilities/datasets/data/imdb.parquet
mlutilities/datasets/data/nyc_taxis.pkl
mlutilities/datasets/data/penguins.pkl
mlutilities/datasets/data/taxis.parquet
mlutilities/datasets/data/titanic.csv
mlutilities/datasets/load_data.py
mlutilities/eda/__init__.py
mlutilities/eda/multivariant.py
mlutilities/eda/multivariant_widget.py
mlutilities/eda/univariant.py
mlutilities/eda/univariant_widget.py
mlutilities/feature_selection.py
mlutilities/model_selection/__init__.py
mlutilities/model_selection/plots.py
mlutilities/preprocessing/__init__.py
mlutilities/preprocessing/impute.py
mlutilities/preprocessing/outlier.py
mlutilities/preprocessing/preprocessing.py
mlutilities/preprocessing/preprocessing_widgets.py
mlutilities/preprocessing/utils.py
mlutilities/regression/__init__.py
mlutilities/regression/models.py
mlutilities/regression/plots.py
mlutilities/regression/regression_widgets.py
mlutilities/regression/utils.py
mlutilities/stats/__init__.py
mlutilities/stats/distributions.py
mlutilities/stats/widgets.py
mlutilities/utils.py
mlutilities_udea-0.0.13.dist-info/METADATA
mlutilities_udea-0.0.13.dist-info/WHEEL
mlutilities_udea-0.0.13.dist-info/RECORD
